idlite/__init__.py
idlite/idlitegen.py
idlite/main.py
idlite/parser.py
idlite/spec.py
idlite/types.py
idlite/unitygen.py
idlite-0.0.11.data/scripts/idlite
idlite-0.0.11.dist-info/DESCRIPTION.rst
idlite-0.0.11.dist-info/METADATA
idlite-0.0.11.dist-info/metadata.json
idlite-0.0.11.dist-info/RECORD
idlite-0.0.11.dist-info/top_level.txt
idlite-0.0.11.dist-info/WHEEL
