Metadata-Version: 2.0
Name: idlite
Version: 0.0.11
Summary: UNKNOWN
Home-page: UNKNOWN
Author: UNKNOWN
Author-email: UNKNOWN
License: UNKNOWN
Platform: UNKNOWN
Classifier: Programming Language :: Python :: 3.3
Classifier: Programming Language :: Python :: 2.7
Requires-Dist: ply
Requires-Dist: Mako
